LICENSE.txt
MANIFEST.in
README.md
RELEASE-VERSION
setup.py
version.py
data/john-smith/ground-truth.yaml
data/john-smith/john-smith-tagged-by-lingpipe-serif-0-197.sc.xz
data/john-smith/original/0/960114.114
data/john-smith/original/0/960228.375
data/john-smith/original/0/960402.459
data/john-smith/original/0/960402.464
data/john-smith/original/0/960513.222
data/john-smith/original/0/960703.505
data/john-smith/original/0/960826.274
data/john-smith/original/0/960826.295
data/john-smith/original/0/960829.192
data/john-smith/original/0/960912.658
data/john-smith/original/0/961014.500
data/john-smith/original/0/970116.458
data/john-smith/original/0/970218.938
data/john-smith/original/0/970307.114
data/john-smith/original/0/970401.380
data/john-smith/original/0/970426.225
data/john-smith/original/0/970703.406
data/john-smith/original/0/970711.171
data/john-smith/original/0/970827.638
data/john-smith/original/0/970926.528
data/john-smith/original/1/960701.288
data/john-smith/original/1/960701.76
data/john-smith/original/1/961106.964
data/john-smith/original/1/970630.222
data/john-smith/original/1/970630.99
data/john-smith/original/10/970416.398
data/john-smith/original/11/960822.669
data/john-smith/original/12/960810.116
data/john-smith/original/13/960919.533
data/john-smith/original/13/960920.10
data/john-smith/original/13/960920.114
data/john-smith/original/13/960920.17
data/john-smith/original/14/970317.818
data/john-smith/original/15/970813.237
data/john-smith/original/15/971222.150
data/john-smith/original/15/971222.198
data/john-smith/original/15/971222.210
data/john-smith/original/16/960103.529
data/john-smith/original/16/960103.581
data/john-smith/original/16/960304.885
data/john-smith/original/16/960409.394
data/john-smith/original/16/960409.428
data/john-smith/original/16/960520.528
data/john-smith/original/16/960524.317
data/john-smith/original/16/960524.444
data/john-smith/original/16/960530.355
data/john-smith/original/16/960530.93
streamcorpus_pipeline.egg-info/PKG-INFO
streamcorpus_pipeline.egg-info/SOURCES.txt
streamcorpus_pipeline.egg-info/dependency_links.txt
streamcorpus_pipeline.egg-info/entry_points.txt
streamcorpus_pipeline.egg-info/not-zip-safe
streamcorpus_pipeline.egg-info/requires.txt
streamcorpus_pipeline.egg-info/top_level.txt
