Metadata-Version: 1.1
Name: streamcorpus-pipeline
Version: 0.7.7
Summary: Tools for building streamcorpus objects, such as those used in TREC.
Home-page: http://github.com/trec-kba/streamcorpus-pipeline
Author: Diffeo, Inc.
Author-email: support@diffeo.com
License: MIT/X11 license http://opensource.org/licenses/MIT
Platform: UNKNOWN
Classifier: Development Status :: 3 - Alpha
Classifier: Topic :: Utilities
Classifier: License :: OSI Approved :: MIT License
